GuardPyCaptcha/Captch.py
GuardPyCaptcha/__init__.py
GuardPyCaptcha-0.1.0.dist-info/METADATA
GuardPyCaptcha-0.1.0.dist-info/WHEEL
GuardPyCaptcha-0.1.0.dist-info/top_level.txt
GuardPyCaptcha-0.1.0.dist-info/RECORD
