Metadata-Version: 2.1
Name: GuardPyCaptcha
Version: 0.1.0
Classifier: Programming Language :: Python :: 3
Classifier: License :: OSI Approved :: MIT License
Classifier: Operating System :: OS Independent
Requires-Python: >=3.6
Requires-Dist: opencv-python
Requires-Dist: keyring
Requires-Dist: cryptography
Requires-Dist: numpy
